yaqd_horiba/VERSION
yaqd_horiba/__init__.py
yaqd_horiba/__version__.py
yaqd_horiba/_horiba_ihr.py
yaqd_horiba/_horiba_mono.py
yaqd_horiba/_microhr.py
yaqd_horiba/horiba-ihr320.avpr
yaqd_horiba/horiba-ihr320.toml
yaqd_horiba/horiba-micro-hr.avpr
yaqd_horiba/horiba-micro-hr.toml
yaqd_horiba-2023.1.0.dist-info/entry_points.txt
yaqd_horiba-2023.1.0.dist-info/LICENSE
yaqd_horiba-2023.1.0.dist-info/WHEEL
yaqd_horiba-2023.1.0.dist-info/METADATA
yaqd_horiba-2023.1.0.dist-info/RECORD
